collector/__init__.py
collector/__main__.py
collector/cli.py
collector/lambda_log_collector.py
collector/utils.py
aws_lambda_log_collector-0.0.9.dist-info/LICENSE
aws_lambda_log_collector-0.0.9.dist-info/METADATA
aws_lambda_log_collector-0.0.9.dist-info/WHEEL
aws_lambda_log_collector-0.0.9.dist-info/entry_points.txt
aws_lambda_log_collector-0.0.9.dist-info/top_level.txt
aws_lambda_log_collector-0.0.9.dist-info/RECORD
