Metadata-Version: 2.1
Name: aws-lambda-log-collector
Version: 0.0.9
Summary: A handy CLI to help you gather Lambda Functions logs
Home-page: https://github.com/mvinii94/aws-lambda-log-collector
Author: Marcus Ramos
Author-email: marcusramos@outlook.ie
License: UNKNOWN
Keywords: aws lambda logs cloud
Platform: UNKNOWN
Classifier: Programming Language :: Python :: 3
Classifier: License :: OSI Approved :: MIT License
Classifier: Operating System :: OS Independent
Requires-Python: >=3.6
Requires-Dist: boto3 (<=1.10.14)
Requires-Dist: botocore (<=1.13.14)
Requires-Dist: click (>=7.0)
